kclib/ParserXLS.py
kclib/YamlFileOperate.py
kclib/__init__.py
kclib-1.0.3.dist-info/METADATA
kclib-1.0.3.dist-info/WHEEL
kclib-1.0.3.dist-info/top_level.txt
kclib-1.0.3.dist-info/RECORD
