Metadata-Version: 2.1
Name: kclib
Version: 1.0.3
Summary: UNKNOWN
Home-page: UNKNOWN
Author: gj
License: GPLv3
Platform: UNKNOWN
Requires-Python: >=3.6
Requires-Dist: xlrd
